aios/README.md
aios/__init__.py
aios/command_executor.py
aios/command_parser.py
aios/context/README.md
aios/context/__init__.py
aios/context/base.py
aios/context/simple_context.py
aios/core/__init__.py
aios/core/schema.py
aios/core/types.py
aios/hooks/__init__.py
aios/hooks/llm.py
aios/hooks/parser.py
aios/hooks/request.py
aios/hooks/utils.py
aios/hooks/validate.py
aios/hooks/stores/__init__.py
aios/hooks/stores/_global.py
aios/hooks/stores/processes.py
aios/hooks/stores/queue.py
aios/hooks/types/__init__.py
aios/hooks/types/hooks.py
aios/hooks/types/llm.py
aios/hooks/types/parser.py
aios/llm_core/README.md
aios/llm_core/llms.py
aios/llm_core/llm_classes/__init__.py
aios/llm_core/llm_classes/base_llm.py
aios/llm_core/llm_classes/bed_rock.py
aios/llm_core/llm_classes/claude_llm.py
aios/llm_core/llm_classes/constant.py
aios/llm_core/llm_classes/gemini_llm.py
aios/llm_core/llm_classes/gpt_llm.py
aios/llm_core/llm_classes/groq_llm.py
aios/llm_core/llm_classes/hf_native_llm.py
aios/llm_core/llm_classes/model_registry.py
aios/llm_core/llm_classes/ollama_llm.py
aios/llm_core/llm_classes/vllm.py
aios/memory/README.md
aios/memory/__init__.py
aios/memory/base.py
aios/memory/lru_k_replacer.py
aios/memory/shared_memory.py
aios/memory/single_memory.py
aios/scheduler/README.md
aios/scheduler/__init__.py
aios/scheduler/base.py
aios/scheduler/fifo_scheduler.py
aios/scheduler/rr_scheduler.py
aios/sdk/__init__.py
aios/sdk/adapter.py
aios/sdk/autogen/__init__.py
aios/sdk/autogen/adapter.py
aios/sdk/autogen/agent_adapter.py
aios/sdk/autogen/client_adapter.py
aios/sdk/interpreter/__init__.py
aios/sdk/interpreter/adapter.py
aios/storage/README.md
aios/storage/__init__.py
aios/storage/base.py
aios/storage/db_storage.py
aios/storage/file_storage.py
aios/utils/README.md
aios/utils/__init__.py
aios/utils/calculator.py
aios/utils/compressor.py
aios/utils/id_generator.py
aios/utils/logger.py
aios/utils/state.py
aios/utils/utils.py
aios/utils/commands/launch.py
aios/utils/commands/top.py
aios_core-0.1.0.dist-info/METADATA
aios_core-0.1.0.dist-info/WHEEL
aios_core-0.1.0.dist-info/entry_points.txt
aios_core-0.1.0.dist-info/licenses/LICENSE
aios_core-0.1.0.dist-info/RECORD
