Metadata-Version: 2.3
Name: aios-core
Version: 0.1.0
Summary: AIOS: LLM Agent Operating System
Project-URL: Homepage, https://github.com/agiresearch/AIOS
Project-URL: Repository, https://github.com/agiresearch/AIOS.git
License: MIT License
License-File: LICENSE
Keywords: llm,os
Classifier: Development Status :: 4 - Beta
Classifier: Intended Audience :: Developers
Classifier: License :: OSI Approved :: MIT License
Classifier: Programming Language :: Python :: 3
Classifier: Programming Language :: Python :: 3.9
Classifier: Programming Language :: Python :: 3.10
Classifier: Programming Language :: Python :: 3.11
Classifier: Topic :: Software Development :: Libraries :: Python Modules
Requires-Python: >=3.9
Requires-Dist: accelerate
Requires-Dist: anthropic
Requires-Dist: click==8.1.7
Requires-Dist: fastapi
Requires-Dist: getch
Requires-Dist: google-generativeai
Requires-Dist: litellm
Requires-Dist: npm
Requires-Dist: ollama
Requires-Dist: openai==1.20.0
Requires-Dist: pandas==2.2.2
Requires-Dist: platformdirs
Requires-Dist: protobuf==4.25.3
Requires-Dist: pydantic==2.7.0
Requires-Dist: pyfzf
Requires-Dist: pympler==1.0.1
Requires-Dist: python-dotenv
Requires-Dist: torch
Requires-Dist: transformers
Requires-Dist: uvicorn
